README.rst
setup.py
boosmap_express/connector.py
boosmap_express/handler.py
boosmap_express/settings.py
django_boosmap_express.egg-info/PKG-INFO
django_boosmap_express.egg-info/SOURCES.txt
django_boosmap_express.egg-info/dependency_links.txt
django_boosmap_express.egg-info/requires.txt
django_boosmap_express.egg-info/top_level.txt