Metadata-Version: 2.1
Name: django-boosmap-express
Version: 1.0.1
Summary: Django Boosmap Integration
Home-page: https://gitlab.com/linets/ecommerce/oms/integrations/django-boosmap/
Author: Linets Development Team
Author-email: dteam@linets.cl
License: MIT
Platform: UNKNOWN
Requires-Python: >=3.7
